{
  "_class": "group",
  "booleanOperation": 0,
  "clippingMaskMode": 0,
  "do_objectID": "2F7E8FB9-59C3-4DD9-899F-4B33478432EC",
  "exportOptions": {
    "_class": "exportOptions",
    "exportFormats": [
    ],
    "includedLayerIds": [
    ],
    "layerOptions": 0,
    "shouldTrim": false
  },
  "frame": {
    "_class": "rect",
    "constrainProportions": false,
    "height": 168,
    "width": 157,
    "x": 0,
    "y": 0
  },
  "hasClickThrough": false,
  "hasClippingMask": false,
  "isFixedToViewport": false,
  "isFlippedHorizontal": false,
  "isFlippedVertical": false,
  "isLocked": false,
  "isVisible": true,
  "layerListExpandedType": 0,
  "layers": [
    {
      "class": "text",
      "id": "5C115157-AB64-4019-9FC3-50819D4425D8"
    },
    {
      "class": "text",
      "id": "FD995291-7C3E-40B1-8C90-31529CF647F7"
    },
    {
      "class": "text",
      "id": "B8EB91CE-1038-439D-ADE7-B39ACF4D43A1"
    }
  ],
  "name": "Wir sind für dich da",
  "nameIsFixed": true,
  "originalObjectID": "2F7E8FB9-59C3-4DD9-899F-4B33478432EC",
  "resizingConstraint": 63,
  "resizingType": 0,
  "rotation": 0,
  "shouldBreakMaskChain": false,
  "style": {
    "_class": "style",
    "endMarkerType": 0,
    "miterLimit": 10,
    "startMarkerType": 0,
    "windingRule": 1
  },
  "userInfo": {
    "com.animaapp.stc-sketch-plugin": {
      "kModelPropertiesKey": {
      }
    }
  }
}