{
  "_class": "shapeGroup",
  "booleanOperation": 0,
  "clippingMaskMode": 0,
  "do_objectID": "8EBC8720-661D-4A2C-AEE0-83C5E1F3BE90",
  "exportOptions": {
    "_class": "exportOptions",
    "exportFormats": [
    ],
    "includedLayerIds": [
    ],
    "layerOptions": 0,
    "shouldTrim": false
  },
  "frame": {
    "_class": "rect",
    "constrainProportions": true,
    "height": 22,
    "width": 22,
    "x": 0,
    "y": 0
  },
  "hasClickThrough": false,
  "hasClippingMask": false,
  "isFixedToViewport": false,
  "isFlippedHorizontal": false,
  "isFlippedVertical": false,
  "isLocked": false,
  "isVisible": true,
  "layerListExpandedType": 1,
  "layers": [
    {
      "class": "shapePath",
      "id": "592246B0-7816-47DA-BAF8-79B59C93FEA8"
    },
    {
      "class": "shapePath",
      "id": "A7DF8819-2649-4F08-927E-08EBC58C21AA"
    },
    {
      "class": "shapePath",
      "id": "36687552-7963-4916-9673-2B1BDBA8B473"
    }
  ],
  "name": "Videoplayer/Volume/loud",
  "nameIsFixed": true,
  "originalObjectID": "8EBC8720-661D-4A2C-AEE0-83C5E1F3BE90",
  "resizingConstraint": 63,
  "resizingType": 0,
  "rotation": 0,
  "shouldBreakMaskChain": false,
  "style": {
    "_class": "style",
    "endMarkerType": 0,
    "fills": [
      {
        "_class": "fill",
        "color": {
          "_class": "color",
          "alpha": 1,
          "blue": 0.615686274509804,
          "green": 0.615686274509804,
          "red": 0.615686274509804
        },
        "fillType": 0,
        "isEnabled": true,
        "noiseIndex": 0,
        "noiseIntensity": 0,
        "patternFillType": 1,
        "patternTileScale": 1
      }
    ],
    "miterLimit": 10,
    "startMarkerType": 0,
    "textStyle": {
      "_class": "textStyle",
      "encodedAttributes": {
        "MSAttributedStringColorAttribute": {
          "_class": "color",
          "alpha": 1,
          "blue": 0.231372549,
          "green": 0.231372549,
          "red": 0.2509803922
        },
        "MSAttributedStringFontAttribute": {
          "_class": "fontDescriptor",
          "attributes": {
            "name": "open-iconic",
            "size": 22
          }
        },
        "kerning": 0,
        "paragraphStyle": {
          "_class": "paragraphStyle",
          "allowsDefaultTighteningForTruncation": 0
        }
      },
      "verticalAlignment": 0
    },
    "windingRule": 1
  },
  "userInfo": {
    "com.animaapp.stc-sketch-plugin": {
      "kModelPropertiesKey": {
        "constraints": {
          "aspectRatio": {
            "constant": 22,
            "enabled": 1,
            "modelID": "constraint_f1f2b617-4b19-452b-b103-6b3549f9d5cf",
            "model_class": "ADModelConstraint",
            "model_version": 0.1,
            "multiplier": 22
          },
          "automatic": 1,
          "modelID": "viewConstraints_69f9d13e-4454-4fa9-8722-0f53241308f8",
          "model_class": "ADModelViewConstraints",
          "model_version": 0.1
        }
      }
    }
  },
  "windingRule": 1
}