{
  "_class": "text",
  "attributedString": {
    "_class": "attributedString",
    "attributes": [
      {
        "_class": "stringAttribute",
        "attributes": {
          "MSAttributedStringColorAttribute": {
            "_class": "color",
            "alpha": 1,
            "blue": 0.231372549,
            "green": 0.231372549,
            "red": 0.2509803922
          },
          "MSAttributedStringFontAttribute": {
            "_class": "fontDescriptor",
            "attributes": {
              "name": "HelveticaNeue-Bold",
              "size": 18
            }
          },
          "kerning": 0,
          "paragraphStyle": {
            "_class": "paragraphStyle",
            "alignment": 0,
            "allowsDefaultTighteningForTruncation": 0,
            "baseWritingDirection": 0,
            "maximumLineHeight": 27,
            "minimumLineHeight": 27,
            "tighteningFactorForTruncation": 0.05
          }
        },
        "length": 86,
        "location": 0
      }
    ],
    "string": "Heading Level 3 Helvetica Neue, bold, 18px\nLine-Spacing 24px, Alignment left or center"
  },
  "automaticallyDrawOnUnderlyingPath": false,
  "booleanOperation": 0,
  "clippingMaskMode": 0,
  "do_objectID": "2F28AA3F-8B2C-44C3-9C8E-4672ED474CC1",
  "dontSynchroniseWithSymbol": false,
  "exportOptions": {
    "_class": "exportOptions",
    "exportFormats": [
    ],
    "includedLayerIds": [
    ],
    "layerOptions": 0,
    "shouldTrim": false
  },
  "frame": {
    "_class": "rect",
    "constrainProportions": false,
    "height": 54,
    "width": 372,
    "x": 52,
    "y": 280
  },
  "glyphBounds": "{{0, 0}, {370, 28}}",
  "hasClippingMask": false,
  "isFixedToViewport": false,
  "isFlippedHorizontal": false,
  "isFlippedVertical": false,
  "isLocked": false,
  "isVisible": true,
  "layerListExpandedType": 0,
  "lineSpacingBehaviour": 2,
  "name": "Heading Level 3 Helv",
  "nameIsFixed": false,
  "resizingConstraint": 45,
  "resizingType": 3,
  "rotation": 0,
  "sharedStyleID": "B0EC47D2-C2E1-4541-977D-F9820AD89EC8",
  "shouldBreakMaskChain": false,
  "style": {
    "_class": "style",
    "do_objectID": "8EE9085C-9B33-42FC-B26D-F70CFE86AED0",
    "endMarkerType": 0,
    "miterLimit": 10,
    "startMarkerType": 0,
    "textStyle": {
      "_class": "textStyle",
      "encodedAttributes": {
        "MSAttributedStringColorAttribute": {
          "_class": "color",
          "alpha": 1,
          "blue": 0.231372549,
          "green": 0.231372549,
          "red": 0.2509803922
        },
        "MSAttributedStringFontAttribute": {
          "_class": "fontDescriptor",
          "attributes": {
            "name": "HelveticaNeue-Bold",
            "size": 18
          }
        },
        "kerning": 0,
        "paragraphStyle": {
          "_class": "paragraphStyle",
          "alignment": 0,
          "allowsDefaultTighteningForTruncation": 0,
          "baseWritingDirection": 0,
          "maximumLineHeight": 27,
          "minimumLineHeight": 27,
          "tighteningFactorForTruncation": 0.05
        }
      },
      "verticalAlignment": 0
    },
    "windingRule": 1
  },
  "textBehaviour": 0,
  "userInfo": {
    "com.animaapp.stc-sketch-plugin": {
      "kModelPropertiesKey": {
        "isAutoWidth": 1
      }
    }
  }
}