{
  "_class": "group",
  "booleanOperation": 0,
  "clippingMaskMode": 0,
  "do_objectID": "DD01DDA4-C7B7-4019-9559-E72C38BFFB00",
  "exportOptions": {
    "_class": "exportOptions",
    "exportFormats": [
    ],
    "includedLayerIds": [
    ],
    "layerOptions": 0,
    "shouldTrim": false
  },
  "frame": {
    "_class": "rect",
    "constrainProportions": false,
    "height": 81,
    "width": 34.99999999999996,
    "x": 0,
    "y": 0
  },
  "hasClickThrough": false,
  "hasClippingMask": false,
  "isFixedToViewport": false,
  "isFlippedHorizontal": false,
  "isFlippedVertical": false,
  "isLocked": false,
  "isVisible": true,
  "layerListExpandedType": 1,
  "layers": [
    {
      "class": "oval",
      "id": "74FD56E6-AED1-41CC-BE17-D31B57622FC5"
    },
    {
      "class": "group",
      "id": "19FD0C22-3CA4-4CF7-B81F-72570285DD53"
    }
  ],
  "name": "Avatar",
  "nameIsFixed": true,
  "resizingConstraint": 63,
  "resizingType": 0,
  "rotation": 0,
  "shouldBreakMaskChain": false,
  "style": {
    "_class": "style",
    "endMarkerType": 0,
    "miterLimit": 10,
    "startMarkerType": 0,
    "windingRule": 1
  }
}